PyLib/__init__.py
PyLib/base.py
lfuu-0.0.1.dist-info/METADATA
lfuu-0.0.1.dist-info/WHEEL
lfuu-0.0.1.dist-info/top_level.txt
lfuu-0.0.1.dist-info/RECORD
