Metadata-Version: 2.1
Name: lfuu
Version: 0.0.1
Summary: This is the simplest module for quick work with files.
Home-page: https://github.com/Vadosik653/libary_test.git
Author: v1ll
Author-email: 312lv5@gmail.com
Project-URL: GitHub, https://github.com/Vadosik653/
Keywords: files speedfiles
Classifier: Programming Language :: Python :: 3.11
Classifier: License :: OSI Approved :: MIT License
Classifier: Operating System :: OS Independent
Requires-Python: >=3.6
